odoo/addons/l10n_br_nfe/README.rst
odoo/addons/l10n_br_nfe/__init__.py
odoo/addons/l10n_br_nfe/__manifest__.py
odoo/addons/l10n_br_nfe/hooks.py
odoo/addons/l10n_br_nfe/constants/nfe.py
odoo/addons/l10n_br_nfe/data/ir_config_parameter.xml
odoo/addons/l10n_br_nfe/demo/company_demo.xml
odoo/addons/l10n_br_nfe/demo/fiscal_document_demo.xml
odoo/addons/l10n_br_nfe/demo/res_users_demo.xml
odoo/addons/l10n_br_nfe/i18n/l10n_br_nfe.pot
odoo/addons/l10n_br_nfe/models/__init__.py
odoo/addons/l10n_br_nfe/models/cest.py
odoo/addons/l10n_br_nfe/models/cfop.py
odoo/addons/l10n_br_nfe/models/document.py
odoo/addons/l10n_br_nfe/models/document_line.py
odoo/addons/l10n_br_nfe/models/document_related.py
odoo/addons/l10n_br_nfe/models/document_type.py
odoo/addons/l10n_br_nfe/models/invalidate_number.py
odoo/addons/l10n_br_nfe/models/nbm.py
odoo/addons/l10n_br_nfe/models/ncm.py
odoo/addons/l10n_br_nfe/models/product_product.py
odoo/addons/l10n_br_nfe/models/res_city.py
odoo/addons/l10n_br_nfe/models/res_company.py
odoo/addons/l10n_br_nfe/models/res_config_settings.py
odoo/addons/l10n_br_nfe/models/res_country.py
odoo/addons/l10n_br_nfe/models/res_country_state.py
odoo/addons/l10n_br_nfe/models/res_partner.py
odoo/addons/l10n_br_nfe/models/tax_ipi_guideline.py
odoo/addons/l10n_br_nfe/models/uom.py
odoo/addons/l10n_br_nfe/readme/CONFIGURE.rst
odoo/addons/l10n_br_nfe/readme/CONTRIBUTORS.rst
odoo/addons/l10n_br_nfe/readme/DESCRIPTION.rst
odoo/addons/l10n_br_nfe/readme/INSTALL.rst
odoo/addons/l10n_br_nfe/readme/ROADMAP.rst
odoo/addons/l10n_br_nfe/readme/USAGE.rst
odoo/addons/l10n_br_nfe/security/nfe_security.xml
odoo/addons/l10n_br_nfe/static/description/icon.png
odoo/addons/l10n_br_nfe/static/description/index.html
odoo/addons/l10n_br_nfe/tests/__init__.py
odoo/addons/l10n_br_nfe/tests/test_account_customer_invoice.py
odoo/addons/l10n_br_nfe/tests/test_account_customer_nfe.py
odoo/addons/l10n_br_nfe/tests/test_account_nfe_refund.py
odoo/addons/l10n_br_nfe/tests/test_account_supplier_nfe.py
odoo12_addon_l10n_br_nfe-12.0.13.4.0.dist-info/METADATA
odoo12_addon_l10n_br_nfe-12.0.13.4.0.dist-info/WHEEL
odoo12_addon_l10n_br_nfe-12.0.13.4.0.dist-info/top_level.txt
odoo12_addon_l10n_br_nfe-12.0.13.4.0.dist-info/RECORD
