Metadata-Version: 2.1
Name: odoo12-addon-l10n-br-nfe
Version: 12.0.13.4.0
Summary: Brazilian Eletronic Invoice NF-e .
Home-page: https://github.com/OCA/l10n-brazil
Author: Akretion,KMEE,Odoo Community Association (OCA)
Author-email: support@odoo-community.org
License: AGPL-3
Platform: UNKNOWN
Classifier: Programming Language :: Python
Classifier: Framework :: Odoo
Classifier: Framework :: Odoo :: 12.0
Classifier: License :: OSI Approved :: GNU Affero General Public License v3
Classifier: Development Status :: 4 - Beta
Requires-Python: >=3.5
Requires-Dist: erpbrasil.assinatura
Requires-Dist: erpbrasil.base
Requires-Dist: erpbrasil.edoc
Requires-Dist: erpbrasil.edoc.pdf
Requires-Dist: erpbrasil.transmissao
Requires-Dist: nfelib
Requires-Dist: odoo12-addon-l10n-br-fiscal
Requires-Dist: odoo12-addon-l10n-br-nfe-spec
Requires-Dist: odoo12-addon-spec-driven-model
Requires-Dist: odoo <12.1dev,>=12.0a
Requires-Dist: xmldiff
